<?xml version="1.0" encoding="UTF-8"?>
<results title="frequencies">
 <result title="frequency" word="{border-style" count="20"/>
 <result title="frequency" word="px;}" count="18"/>
 <result title="frequency" word="#ffffff;}" count="17"/>
 <result title="frequency" word="symptoms" count="16"/>
 <result title="frequency" word="neurological" count="12"/>
 <result title="frequency" word="celiac" count="10"/>
 <result title="frequency" word="motor" count="10"/>
 <result title="frequency" word="described" count="8"/>
 <result title="frequency" word="patients" count="8"/>
 <result title="frequency" word="px;" count="8"/>
 <result title="frequency" word="{font-family" count="8"/>
 <result title="frequency" word="disease" count="7"/>
 <result title="frequency" word="disease." count="7"/>
 <result title="frequency" word="font-size" count="7"/>
 <result title="frequency" word="gastrointestinal" count="7"/>
 <result title="frequency" word="manifestations" count="7"/>
 <result title="frequency" word="Neurological" count="6"/>
 <result title="frequency" word="double;" count="6"/>
 <result title="frequency" word="presenting" count="6"/>
 <result title="frequency" word="regression" count="6"/>
 <result title="frequency" word="reported" count="6"/>
 <result title="frequency" word="Hadjivassiliou" count="5"/>
 <result title="frequency" word="antibodies" count="5"/>
 <result title="frequency" word="border-color" count="5"/>
 <result title="frequency" word="border-width" count="5"/>
 <result title="frequency" word="children" count="5"/>
 <result title="frequency" word="examination" count="5"/>
 <result title="frequency" word="revealed" count="5"/>
 <result title="frequency" word="solid;" count="5"/>
 <result title="frequency" word="{font-style" count="5"/>
 <result title="frequency" word="{font-weight" count="5"/>
 <result title="frequency" word="CD." count="4"/>
 <result title="frequency" word="Case" count="4"/>
 <result title="frequency" word="Celiac" count="4"/>
 <result title="frequency" word="associated" count="4"/>
 <result title="frequency" word="bold" count="4"/>
 <result title="frequency" word="children." count="4"/>
 <result title="frequency" word="courier;" count="4"/>
 <result title="frequency" word="elevated" count="4"/>
 <result title="frequency" word="em;" count="4"/>
 <result title="frequency" word="gluten" count="4"/>
 <result title="frequency" word="pt;}" count="4"/>
 <result title="frequency" word="showed" count="4"/>
 <result title="frequency" word="symptoms." count="4"/>
 <result title="frequency" word="vomiting" count="4"/>
</results>
