<?xml version="1.0" encoding="UTF-8"?>
<results title="frequencies">
 <result title="frequency" word="migraine" count="69"/>
 <result title="frequency" word="GPs" count="68"/>
 <result title="frequency" word="pediatric" count="44"/>
 <result title="frequency" word="treatment" count="44"/>
 <result title="frequency" word="ibuprofen" count="41"/>
 <result title="frequency" word="guidelines" count="38"/>
 <result title="frequency" word="preventive" count="32"/>
 <result title="frequency" word="children" count="31"/>
 <result title="frequency" word="management" count="30"/>
 <result title="frequency" word="headache" count="29"/>
 <result title="frequency" word="[.–.]" count="26"/>
 <result title="frequency" word="acute" count="23"/>
 <result title="frequency" word="study" count="22"/>
 <result title="frequency" word="Question" count="20"/>
 <result title="frequency" word="{border-style" count="20"/>
 <result title="frequency" word="px;}" count="18"/>
 <result title="frequency" word="#ffffff;}" count="17"/>
 <result title="frequency" word="drug" count="16"/>
 <result title="frequency" word="therapeutic" count="16"/>
 <result title="frequency" word="Headache" count="15"/>
 <result title="frequency" word="daily" count="15"/>
 <result title="frequency" word="GPs." count="14"/>
 <result title="frequency" word="adolescents" count="13"/>
 <result title="frequency" word="intention" count="13"/>
 <result title="frequency" word="medication" count="13"/>
 <result title="frequency" word="practice" count="13"/>
 <result title="frequency" word="Neurology" count="12"/>
 <result title="frequency" word="abortive" count="12"/>
 <result title="frequency" word="attacks" count="12"/>
 <result title="frequency" word="general" count="12"/>
 <result title="frequency" word="prescribed" count="12"/>
 <result title="frequency" word="therapy" count="12"/>
 <result title="frequency" word="./j.-...x" count="11"/>
 <result title="frequency" word="clinical" count="11"/>
 <result title="frequency" word="did" count="11"/>
 <result title="frequency" word="knowledge" count="11"/>
 <result title="frequency" word="urban" count="11"/>
 <result title="frequency" word="(%)" count="10"/>
 <result title="frequency" word="first-line" count="10"/>
 <result title="frequency" word="patients" count="10"/>
 <result title="frequency" word="prescribing" count="10"/>
 <result title="frequency" word="Chronic" count="9"/>
 <result title="frequency" word="patient" count="9"/>
 <result title="frequency" word="recommended" count="9"/>
 <result title="frequency" word="rural" count="9"/>
 <result title="frequency" word="study," count="9"/>
 <result title="frequency" word="France" count="8"/>
 <result title="frequency" word="Med" count="8"/>
 <result title="frequency" word="Neurol" count="8"/>
 <result title="frequency" word="dose" count="8"/>
 <result title="frequency" word="doses" count="8"/>
 <result title="frequency" word="migraines" count="8"/>
 <result title="frequency" word="prescribe" count="8"/>
 <result title="frequency" word="previous" count="8"/>
 <result title="frequency" word="px;" count="8"/>
 <result title="frequency" word="questions" count="8"/>
 <result title="frequency" word="stated" count="8"/>
 <result title="frequency" word="{font-family" count="8"/>
 <result title="frequency" word="American" count="7"/>
 <result title="frequency" word="Ibuprofen" count="7"/>
 <result title="frequency" word="disability" count="7"/>
 <result title="frequency" word="drugs" count="7"/>
 <result title="frequency" word="font-size" count="7"/>
 <result title="frequency" word="lack" count="7"/>
 <result title="frequency" word="read" count="7"/>
 <result title="frequency" word="reference" count="7"/>
 <result title="frequency" word="sample" count="7"/>
 <result title="frequency" word="Cephalalgia" count="6"/>
 <result title="frequency" word="Child" count="6"/>
 <result title="frequency" word="Migraine" count="6"/>
 <result title="frequency" word="Practice" count="6"/>
 <result title="frequency" word="[.–]" count="6"/>
 <result title="frequency" word="adolescents:" count="6"/>
 <result title="frequency" word="adverse" count="6"/>
 <result title="frequency" word="and/or" count="6"/>
 <result title="frequency" word="answer" count="6"/>
 <result title="frequency" word="awareness" count="6"/>
 <result title="frequency" word="chronic" count="6"/>
 <result title="frequency" word="double;" count="6"/>
 <result title="frequency" word="initiate" count="6"/>
 <result title="frequency" word="migraine." count="6"/>
 <result title="frequency" word="referral" count="6"/>
 <result title="frequency" word="risk" count="6"/>
 <result title="frequency" word="second-line" count="6"/>
 <result title="frequency" word="start" count="6"/>
 <result title="frequency" word="therapy." count="6"/>
 <result title="frequency" word="years" count="6"/>
 <result title="frequency" word="Aspirin" count="5"/>
 <result title="frequency" word="Failure" count="5"/>
 <result title="frequency" word="Study" count="5"/>
 <result title="frequency" word="acetaminophen" count="5"/>
 <result title="frequency" word="attack" count="5"/>
 <result title="frequency" word="attack," count="5"/>
 <result title="frequency" word="aware" count="5"/>
 <result title="frequency" word="body" count="5"/>
 <result title="frequency" word="border-color" count="5"/>
 <result title="frequency" word="border-width" count="5"/>
 <result title="frequency" word="care" count="5"/>
 <result title="frequency" word="child" count="5"/>
 <result title="frequency" word="concerned" count="5"/>
 <result title="frequency" word="conducted" count="5"/>
 <result title="frequency" word="considered" count="5"/>
 <result title="frequency" word="consultation" count="5"/>
 <result title="frequency" word="data" count="5"/>
 <result title="frequency" word="disease" count="5"/>
 <result title="frequency" word="effective" count="5"/>
 <result title="frequency" word="headaches" count="5"/>
 <result title="frequency" word="overuse" count="5"/>
 <result title="frequency" word="pain" count="5"/>
 <result title="frequency" word="practitioners" count="5"/>
 <result title="frequency" word="prescription" count="5"/>
 <result title="frequency" word="rate" count="5"/>
 <result title="frequency" word="second" count="5"/>
 <result title="frequency" word="significant" count="5"/>
 <result title="frequency" word="solid;" count="5"/>
 <result title="frequency" word="specialist" count="5"/>
 <result title="frequency" word="weight" count="5"/>
 <result title="frequency" word="{font-style" count="5"/>
 <result title="frequency" word="{font-weight" count="5"/>
 <result title="frequency" word="(Fig." count="4"/>
 <result title="frequency" word="Academy" count="4"/>
 <result title="frequency" word="Clinical" count="4"/>
 <result title="frequency" word="Committee" count="4"/>
 <result title="frequency" word="Cuvellier" count="4"/>
 <result title="frequency" word="France." count="4"/>
 <result title="frequency" word="French" count="4"/>
 <result title="frequency" word="Health" count="4"/>
 <result title="frequency" word="Hershey" count="4"/>
 <result title="frequency" word="Opioids" count="4"/>
 <result title="frequency" word="Paracetamol" count="4"/>
 <result title="frequency" word="Quality" count="4"/>
 <result title="frequency" word="Reasons" count="4"/>
 <result title="frequency" word="Sumatriptan" count="4"/>
 <result title="frequency" word="Table" count="4"/>
 <result title="frequency" word="Yes" count="4"/>
 <result title="frequency" word="abuse" count="4"/>
 <result title="frequency" word="age" count="4"/>
 <result title="frequency" word="agreeing" count="4"/>
 <result title="frequency" word="analgesic" count="4"/>
 <result title="frequency" word="apply" count="4"/>
 <result title="frequency" word="appropriate" count="4"/>
 <result title="frequency" word="assess" count="4"/>
 <result title="frequency" word="behavior" count="4"/>
 <result title="frequency" word="bold" count="4"/>
 <result title="frequency" word="childhood" count="4"/>
 <result title="frequency" word="children," count="4"/>
 <result title="frequency" word="choice" count="4"/>
 <result title="frequency" word="compared" count="4"/>
 <result title="frequency" word="courier;" count="4"/>
 <result title="frequency" word="course" count="4"/>
 <result title="frequency" word="dosage" count="4"/>
 <result title="frequency" word="em;" count="4"/>
 <result title="frequency" word="evidence" count="4"/>
 <result title="frequency" word="fact" count="4"/>
 <result title="frequency" word="guidelines:" count="4"/>
 <result title="frequency" word="impact" count="4"/>
 <result title="frequency" word="included" count="4"/>
 <result title="frequency" word="knew" count="4"/>
 <result title="frequency" word="matter" count="4"/>
 <result title="frequency" word="mean" count="4"/>
 <result title="frequency" word="men" count="4"/>
 <result title="frequency" word="migraine," count="4"/>
 <result title="frequency" word="neurologist" count="4"/>
 <result title="frequency" word="new" count="4"/>
 <result title="frequency" word="population" count="4"/>
 <result title="frequency" word="prevalence" count="4"/>
 <result title="frequency" word="pt;}" count="4"/>
 <result title="frequency" word="published" count="4"/>
 <result title="frequency" word="safety" count="4"/>
 <result title="frequency" word="showed" count="4"/>
 <result title="frequency" word="single" count="4"/>
 <result title="frequency" word="studies" count="4"/>
 <result title="frequency" word="survey" count="4"/>
 <result title="frequency" word="treatment," count="4"/>
 <result title="frequency" word="use" count="4"/>
</results>
