<?xml version="1.0" encoding="UTF-8"?>
<results title="frequencies">
 <result title="frequency" word="patients" count="61"/>
 <result title="frequency" word="mIP" count="43"/>
 <result title="frequency" word="MRI" count="26"/>
 <result title="frequency" word="brain" count="25"/>
 <result title="frequency" word="images" count="24"/>
 <result title="frequency" word="(.%)" count="21"/>
 <result title="frequency" word="EEG" count="21"/>
 <result title="frequency" word="epileptic" count="21"/>
 <result title="frequency" word="(.)" count="20"/>
 <result title="frequency" word="{border-style" count="20"/>
 <result title="frequency" word="blood" count="18"/>
 <result title="frequency" word="imaging" count="18"/>
 <result title="frequency" word="px;}" count="18"/>
 <result title="frequency" word="seizure" count="18"/>
 <result title="frequency" word="showed" count="18"/>
 <result title="frequency" word="#ffffff;}" count="17"/>
 <result title="frequency" word="epilepsy" count="15"/>
 <result title="frequency" word="using" count="15"/>
 <result title="frequency" word="focal" count="14"/>
 <result title="frequency" word="findings" count="13"/>
 <result title="frequency" word="patients." count="13"/>
 <result title="frequency" word="semiology" count="13"/>
 <result title="frequency" word="SWI" count="12"/>
 <result title="frequency" word="asymmetric" count="12"/>
 <result title="frequency" word="image" count="12"/>
 <result title="frequency" word="venous" count="11"/>
 <result title="frequency" word="ImageJ" count="10"/>
 <result title="frequency" word="study" count="10"/>
 <result title="frequency" word="susceptibility" count="10"/>
 <result title="frequency" word="cerebral" count="9"/>
 <result title="frequency" word="partial" count="9"/>
 <result title="frequency" word="SPECT" count="8"/>
 <result title="frequency" word="difference" count="8"/>
 <result title="frequency" word="hours" count="8"/>
 <result title="frequency" word="increased" count="8"/>
 <result title="frequency" word="magnetic" count="8"/>
 <result title="frequency" word="px;" count="8"/>
 <result title="frequency" word="{font-family" count="8"/>
 <result title="frequency" word="font-size" count="7"/>
 <result title="frequency" word="hemispheres" count="7"/>
 <result title="frequency" word="ictal" count="7"/>
 <result title="frequency" word="intensity" count="7"/>
 <result title="frequency" word="vascularity" count="7"/>
 <result title="frequency" word="vessels" count="7"/>
 <result title="frequency" word="abnormalities" count="6"/>
 <result title="frequency" word="abnormalities." count="6"/>
 <result title="frequency" word="asymmetry" count="6"/>
 <result title="frequency" word="double;" count="6"/>
 <result title="frequency" word="epilepsy." count="6"/>
 <result title="frequency" word="hypervascularity" count="6"/>
 <result title="frequency" word="minimum" count="6"/>
 <result title="frequency" word="performed" count="6"/>
 <result title="frequency" word="perfusion" count="6"/>
 <result title="frequency" word="received" count="6"/>
 <result title="frequency" word="remaining" count="6"/>
 <result title="frequency" word="right" count="6"/>
 <result title="frequency" word="seizures" count="6"/>
 <result title="frequency" word="(%)" count="5"/>
 <result title="frequency" word="Brain" count="5"/>
 <result title="frequency" word="Concordance" count="5"/>
 <result title="frequency" word="However," count="5"/>
 <result title="frequency" word="Neurol" count="5"/>
 <result title="frequency" word="T-weighted" count="5"/>
 <result title="frequency" word="Table" count="5"/>
 <result title="frequency" word="border-color" count="5"/>
 <result title="frequency" word="border-width" count="5"/>
 <result title="frequency" word="data" count="5"/>
 <result title="frequency" word="differences" count="5"/>
 <result title="frequency" word="headache" count="5"/>
 <result title="frequency" word="important" count="5"/>
 <result title="frequency" word="increase" count="5"/>
 <result title="frequency" word="infarction" count="5"/>
 <result title="frequency" word="patients," count="5"/>
 <result title="frequency" word="solid;" count="5"/>
 <result title="frequency" word="underwent" count="5"/>
 <result title="frequency" word="useful" count="5"/>
 <result title="frequency" word="{font-style" count="5"/>
 <result title="frequency" word="{font-weight" count="5"/>
 <result title="frequency" word="&amp;gt;%" count="4"/>
 <result title="frequency" word="Fig." count="4"/>
 <result title="frequency" word="MRI," count="4"/>
 <result title="frequency" word="Thirty-one" count="4"/>
 <result title="frequency" word="bold" count="4"/>
 <result title="frequency" word="children" count="4"/>
 <result title="frequency" word="clinical" count="4"/>
 <result title="frequency" word="comprised" count="4"/>
 <result title="frequency" word="concordant" count="4"/>
 <result title="frequency" word="consistent" count="4"/>
 <result title="frequency" word="courier;" count="4"/>
 <result title="frequency" word="diagnosis" count="4"/>
 <result title="frequency" word="did" count="4"/>
 <result title="frequency" word="em;" count="4"/>
 <result title="frequency" word="enrolled" count="4"/>
 <result title="frequency" word="epilepsy," count="4"/>
 <result title="frequency" word="epileptogenic" count="4"/>
 <result title="frequency" word="identify" count="4"/>
 <result title="frequency" word="including" count="4"/>
 <result title="frequency" word="left" count="4"/>
 <result title="frequency" word="lesions" count="4"/>
 <result title="frequency" word="lobe" count="4"/>
 <result title="frequency" word="neurological" count="4"/>
 <result title="frequency" word="observed" count="4"/>
 <result title="frequency" word="obtained" count="4"/>
 <result title="frequency" word="onset" count="4"/>
 <result title="frequency" word="pediatric" count="4"/>
 <result title="frequency" word="projection" count="4"/>
 <result title="frequency" word="pt;}" count="4"/>
 <result title="frequency" word="seizures." count="4"/>
 <result title="frequency" word="signal" count="4"/>
 <result title="frequency" word="susceptibility-weighted" count="4"/>
 <result title="frequency" word="symptoms" count="4"/>
 <result title="frequency" word="time" count="4"/>
 <result title="frequency" word="used" count="4"/>
 <result title="frequency" word="vessel" count="4"/>
</results>
