{
  "id": [
    "19705059"
  ],
  "source": [
    "MED"
  ],
  "pmid": [
    "19705059"
  ],
  "pmcid": [
    "PMC3452095"
  ],
  "doi": [
    "10.1007/s10194-009-0147-x"
  ],
  "title": [
    "Trigger factors in childhood migraine: a clinic-based study from eastern India."
  ],
  "authorString": [
    "Chakravarty A, Mukherjee A, Roy D."
  ],
  "authorList": [
    {
      "author": [
        {
          "fullName": [
            "Chakravarty A"
          ],
          "firstName": [
            "Ambar"
          ],
          "lastName": [
            "Chakravarty"
          ],
          "initials": [
            "A"
          ],
          "affiliation": [
            "Department of Neurology, Vivekananda Institute of Medical Sciences, Calcutta, India. saschakra@yahoo.com"
          ]
        },
        {
          "fullName": [
            "Mukherjee A"
          ],
          "firstName": [
            "A"
          ],
          "lastName": [
            "Mukherjee"
          ],
          "initials": [
            "A"
          ]
        },
        {
          "fullName": [
            "Roy D"
          ],
          "firstName": [
            "D"
          ],
          "lastName": [
            "Roy"
          ],
          "initials": [
            "D"
          ]
        }
      ]
    }
  ],
  "journalInfo": [
    {
      "issue": [
        "5"
      ],
      "volume": [
        "10"
      ],
      "journalIssueId": [
        "1650930"
      ],
      "dateOfPublication": [
        "2009 Oct"
      ],
      "monthOfPublication": [
        "10"
      ],
      "yearOfPublication": [
        "2009"
      ],
      "printPublicationDate": [
        "2009-10-01"
      ],
      "journal": [
        {
          "title": [
            "The journal of headache and pain"
          ],
          "ISOAbbreviation": [
            "J Headache Pain"
          ],
          "medlineAbbreviation": [
            "J Headache Pain"
          ],
          "NLMid": [
            "100940562"
          ],
          "ISSN": [
            "1129-2369"
          ],
          "ESSN": [
            "1129-2377"
          ]
        }
      ]
    }
  ],
  "pubYear": [
    "2009"
  ],
  "pageInfo": [
    "375-380"
  ],
  "abstractText": [
    "Literature on triggers of childhood migraine is sparse. This study was carried out in 200 children (7-15 years) with migraine from a metropolitan city in Eastern India, both retrospectively and prospectively, with headache diaries to note the incidence of various triggers. In the retrospective study, triggers could be identified in 94% of subjects while in 100% of children in the prospective part of the study more than one trigger could be identified. Most migraine triggers identified were environmental (sun exposure, hot humid weather, smoke and noise) and stress related (school stress mostly). Quite often these operated concurrently to precipitate individual migraine attacks."
  ],
  "affiliation": [
    "Department of Neurology, Vivekananda Institute of Medical Sciences, Calcutta, India. saschakra@yahoo.com"
  ],
  "language": [
    "eng"
  ],
  "pubModel": [
    "Print-Electronic"
  ],
  "pubTypeList": [
    {
      "pubType": [
        "research-article",
        "Journal Article"
      ]
    }
  ],
  "meshHeadingList": [
    {
      "meshHeading": [
        {
          "majorTopic_YN": [
            "N"
          ],
          "descriptorName": [
            "Humans"
          ]
        },
        {
          "majorTopic_YN": [
            "N"
          ],
          "descriptorName": [
            "Stress, Psychological"
          ],
          "meshQualifierList": [
            {
              "meshQualifier": [
                {
                  "abbreviation": [
                    "CO"
                  ],
                  "qualifierName": [
                    "complications"
                  ],
                  "majorTopic_YN": [
                    "Y"
                  ]
                }
              ]
            }
          ]
        },
        {
          "majorTopic_YN": [
            "N"
          ],
          "descriptorName": [
            "Environmental Exposure"
          ],
          "meshQualifierList": [
            {
              "meshQualifier": [
                {
                  "abbreviation": [
                    "AE"
                  ],
                  "qualifierName": [
                    "adverse effects"
                  ],
                  "majorTopic_YN": [
                    "Y"
                  ]
                }
              ]
            }
          ]
        },
        {
          "majorTopic_YN": [
            "N"
          ],
          "descriptorName": [
            "Adolescent"
          ]
        },
        {
          "majorTopic_YN": [
            "N"
          ],
          "descriptorName": [
            "Child"
          ]
        },
        {
          "majorTopic_YN": [
            "N"
          ],
          "descriptorName": [
            "India"
          ]
        },
        {
          "majorTopic_YN": [
            "N"
          ],
          "descriptorName": [
            "Female"
          ]
        },
        {
          "majorTopic_YN": [
            "N"
          ],
          "descriptorName": [
            "Male"
          ]
        },
        {
          "majorTopic_YN": [
            "N"
          ],
          "descriptorName": [
            "Migraine Disorders"
          ],
          "meshQualifierList": [
            {
              "meshQualifier": [
                {
                  "abbreviation": [
                    "ET"
                  ],
                  "qualifierName": [
                    "etiology"
                  ],
                  "majorTopic_YN": [
                    "Y"
                  ]
                }
              ]
            }
          ]
        }
      ]
    }
  ],
  "subsetList": [
    {
      "subset": [
        {
          "code": [
            "IM"
          ],
          "name": [
            "Index Medicus"
          ]
        }
      ]
    }
  ],
  "fullTextUrlList": [
    {
      "fullTextUrl": [
        {
          "availability": [
            "Free"
          ],
          "availabilityCode": [
            "F"
          ],
          "documentStyle": [
            "pdf"
          ],
          "site": [
            "PubMedCentral"
          ],
          "url": [
            "https://www.ncbi.nlm.nih.gov/pmc/articles/pmid/19705059/pdf/?tool=EBI"
          ]
        },
        {
          "availability": [
            "Free"
          ],
          "availabilityCode": [
            "F"
          ],
          "documentStyle": [
            "html"
          ],
          "site": [
            "PubMedCentral"
          ],
          "url": [
            "https://www.ncbi.nlm.nih.gov/pmc/articles/pmid/19705059/?tool=EBI"
          ]
        },
        {
          "availability": [
            "Subscription required"
          ],
          "availabilityCode": [
            "S"
          ],
          "documentStyle": [
            "doi"
          ],
          "site": [
            "DOI"
          ],
          "url": [
            "https://doi.org/10.1007/s10194-009-0147-x"
          ]
        },
        {
          "availability": [
            "Open access"
          ],
          "availabilityCode": [
            "OA"
          ],
          "documentStyle": [
            "html"
          ],
          "site": [
            "Europe_PMC"
          ],
          "url": [
            "https://europepmc.org/articles/PMC3452095"
          ]
        },
        {
          "availability": [
            "Open access"
          ],
          "availabilityCode": [
            "OA"
          ],
          "documentStyle": [
            "pdf"
          ],
          "site": [
            "Europe_PMC"
          ],
          "url": [
            "https://europepmc.org/articles/PMC3452095?pdf=render"
          ]
        }
      ]
    }
  ],
  "isOpenAccess": [
    "Y"
  ],
  "inEPMC": [
    "Y"
  ],
  "inPMC": [
    "Y"
  ],
  "hasPDF": [
    "Y"
  ],
  "hasBook": [
    "N"
  ],
  "hasSuppl": [
    "N"
  ],
  "citedByCount": [
    "17"
  ],
  "hasData": [
    "N"
  ],
  "hasReferences": [
    "Y"
  ],
  "hasTextMinedTerms": [
    "Y"
  ],
  "hasDbCrossReferences": [
    "N"
  ],
  "hasLabsLinks": [
    "Y"
  ],
  "authMan": [
    "N"
  ],
  "epmcAuthMan": [
    "N"
  ],
  "nihAuthMan": [
    "N"
  ],
  "hasTMAccessionNumbers": [
    "N"
  ],
  "dateOfCompletion": [
    "2009-11-17"
  ],
  "dateOfCreation": [
    "2009-08-26"
  ],
  "firstIndexDate": [
    "2009-11-18"
  ],
  "fullTextReceivedDate": [
    "2012-12-01"
  ],
  "dateOfRevision": [
    "2018-09-14"
  ],
  "electronicPublicationDate": [
    "2009-08-25"
  ],
  "firstPublicationDate": [
    "2009-08-25"
  ]
}