<?xml version="1.0" encoding="UTF-8"?>
<snippetsTree>
 <snippets file="migraine/PMC6681503/results/word/frequencies/results.xml">
  <result title="frequency" word="vitamin" count="114"/>
  <result title="frequency" word="migraine" count="63"/>
  <result title="frequency" word="patients" count="46"/>
  <result title="frequency" word="levels" count="40"/>
  <result title="frequency" word="(–)" count="29"/>
  <result title="frequency" word="Vitamin" count="29"/>
  <result title="frequency" word="Migraine" count="26"/>
  <result title="frequency" word="deficiency" count="24"/>
  <result title="frequency" word="group" count="22"/>
 </snippets>
</snippetsTree>
