{
  "id": [
    "PMC6272043"
  ],
  "source": [
    "PMC"
  ],
  "pmcid": [
    "PMC6272043"
  ],
  "doi": [
    "10.1111/jvim.15319"
  ],
  "title": [
    "2018 ACVIM Forum Research Abstract Program: Seattle, Washington, June 14 ‐ 15, 2018."
  ],
  "authorIdList": [
    {
      "authorId": [
        {
          "_": "0000-0002-3366-2110",
          "$": {
            "type": "ORCID"
          }
        }
      ]
    }
  ],
  "journalInfo": [
    {
      "issue": [
        "6"
      ],
      "volume": [
        "32"
      ],
      "journalIssueId": [
        "2758494"
      ],
      "dateOfPublication": [
        "2018 "
      ],
      "monthOfPublication": [
        "0"
      ],
      "yearOfPublication": [
        "2018"
      ],
      "printPublicationDate": [
        "2018-01-01"
      ],
      "journal": [
        {
          "title": [
            "Journal of veterinary internal medicine"
          ],
          "ISOAbbreviation": [
            "J. Vet. Intern. Med."
          ],
          "medlineAbbreviation": [
            "J Vet Intern Med"
          ],
          "NLMid": [
            "8708660"
          ],
          "ISSN": [
            "0891-6640"
          ],
          "ESSN": [
            "1939-1676"
          ]
        }
      ]
    }
  ],
  "pubYear": [
    "2018"
  ],
  "pageInfo": [
    "2144-2309"
  ],
  "language": [
    "eng"
  ],
  "pubModel": [
    "Undetermined"
  ],
  "pubTypeList": [
    {
      "pubType": [
        "Abstract"
      ]
    }
  ],
  "fullTextUrlList": [
    {
      "fullTextUrl": [
        {
          "availability": [
            "Free"
          ],
          "availabilityCode": [
            "F"
          ],
          "documentStyle": [
            "html"
          ],
          "site": [
            "PubMedCentral"
          ],
          "url": [
            "https://www.ncbi.nlm.nih.gov/pmc/articles/PMC6272043/?tool=EBI"
          ]
        },
        {
          "availability": [
            "Free"
          ],
          "availabilityCode": [
            "F"
          ],
          "documentStyle": [
            "html"
          ],
          "site": [
            "Europe_PMC"
          ],
          "url": [
            "https://europepmc.org/articles/PMC6272043"
          ]
        }
      ]
    }
  ],
  "isOpenAccess": [
    "Y"
  ],
  "inEPMC": [
    "Y"
  ],
  "inPMC": [
    "Y"
  ],
  "hasPDF": [
    "Y"
  ],
  "hasBook": [
    "N"
  ],
  "hasSuppl": [
    "N"
  ],
  "citedByCount": [
    "0"
  ],
  "hasData": [
    "N"
  ],
  "hasReferences": [
    "N"
  ],
  "hasTextMinedTerms": [
    "Y"
  ],
  "hasDbCrossReferences": [
    "N"
  ],
  "hasLabsLinks": [
    "N"
  ],
  "license": [
    "cc by-nc"
  ],
  "authMan": [
    "N"
  ],
  "epmcAuthMan": [
    "N"
  ],
  "nihAuthMan": [
    "N"
  ],
  "hasTMAccessionNumbers": [
    "N"
  ],
  "dateOfCreation": [
    "2018-12-11"
  ],
  "firstIndexDate": [
    "2018-12-11"
  ],
  "fullTextReceivedDate": [
    "2018-12-11"
  ],
  "dateOfRevision": [
    "2019-09-30"
  ],
  "electronicPublicationDate": [
    "2018-10-25"
  ],
  "firstPublicationDate": [
    "2018-10-25"
  ]
}