<?xml version="1.0" encoding="UTF-8"?>
<snippetsTree>
 <snippets file="migraine/PMC5844943/results/word/frequencies/results.xml">
  <result title="frequency" word="headache" count="39"/>
  <result title="frequency" word="cognitive" count="33"/>
  <result title="frequency" word="non-verbal" count="27"/>
  <result title="frequency" word="(.)" count="26"/>
  <result title="frequency" word="memory" count="25"/>
  <result title="frequency" word="attacks" count="22"/>
  <result title="frequency" word="attention" count="22"/>
  <result title="frequency" word="children" count="21"/>
 </snippets>
</snippetsTree>
