<?xml version="1.0" encoding="UTF-8"?>
<results title="frequencies">
 <result title="frequency" word="musical" count="63"/>
 <result title="frequency" word="latency" count="55"/>
 <result title="frequency" word="musicians" count="50"/>
 <result title="frequency" word="auditory" count="49"/>
 <result title="frequency" word="ability" count="46"/>
 <result title="frequency" word="visual" count="35"/>
 <result title="frequency" word="processing" count="34"/>
 <result title="frequency" word="cognitive" count="28"/>
 <result title="frequency" word="ERP" count="27"/>
 <result title="frequency" word="test" count="26"/>
 <result title="frequency" word="(ms)" count="24"/>
 <result title="frequency" word="different" count="24"/>
 <result title="frequency" word="group" count="24"/>
 <result title="frequency" word="results" count="22"/>
 <result title="frequency" word="{border-style" count="20"/>
 <result title="frequency" word="pitch" count="19"/>
 <result title="frequency" word="subjects" count="19"/>
 <result title="frequency" word="habituation" count="18"/>
 <result title="frequency" word="px;}" count="18"/>
 <result title="frequency" word="score" count="18"/>
 <result title="frequency" word="training" count="18"/>
 <result title="frequency" word="#ffffff;}" count="17"/>
 <result title="frequency" word="studies" count="17"/>
 <result title="frequency" word="music" count="16"/>
 <result title="frequency" word="non-musicians" count="16"/>
 <result title="frequency" word="stimuli" count="16"/>
 <result title="frequency" word="stimulus" count="16"/>
 <result title="frequency" word="event-related" count="15"/>
 <result title="frequency" word="evoked" count="15"/>
 <result title="frequency" word="absolute" count="14"/>
 <result title="frequency" word="latencies" count="13"/>
 <result title="frequency" word="shown" count="13"/>
 <result title="frequency" word="Seashore" count="12"/>
 <result title="frequency" word="showed" count="12"/>
 <result title="frequency" word="significantly" count="12"/>
 <result title="frequency" word="differences" count="11"/>
 <result title="frequency" word="higher" count="11"/>
 <result title="frequency" word="potentials" count="11"/>
 <result title="frequency" word="study" count="11"/>
 <result title="frequency" word="target" count="11"/>
 <result title="frequency" word="ability." count="10"/>
 <result title="frequency" word="correlation" count="10"/>
 <result title="frequency" word="measured" count="10"/>
 <result title="frequency" word="non-musicians." count="10"/>
 <result title="frequency" word="used" count="10"/>
 <result title="frequency" word="Musical" count="9"/>
 <result title="frequency" word="amusia" count="9"/>
 <result title="frequency" word="brain" count="9"/>
 <result title="frequency" word="groups" count="8"/>
 <result title="frequency" word="pitch," count="8"/>
 <result title="frequency" word="presented" count="8"/>
 <result title="frequency" word="processing." count="8"/>
 <result title="frequency" word="px;" count="8"/>
 <result title="frequency" word="response" count="8"/>
 <result title="frequency" word="shorter" count="8"/>
 <result title="frequency" word="time" count="8"/>
 <result title="frequency" word="tones" count="8"/>
 <result title="frequency" word="visually" count="8"/>
 <result title="frequency" word="{font-family" count="8"/>
 <result title="frequency" word="&amp;lt;" count="7"/>
 <result title="frequency" word="Table" count="7"/>
 <result title="frequency" word="Zerssen" count="7"/>
 <result title="frequency" word="amplitude" count="7"/>
 <result title="frequency" word="associated" count="7"/>
 <result title="frequency" word="certain" count="7"/>
 <result title="frequency" word="decreased" count="7"/>
 <result title="frequency" word="did" count="7"/>
 <result title="frequency" word="faster" count="7"/>
 <result title="frequency" word="font-size" count="7"/>
 <result title="frequency" word="mean" count="7"/>
 <result title="frequency" word="memory" count="7"/>
 <result title="frequency" word="study," count="7"/>
 <result title="frequency" word="tests" count="7"/>
 <result title="frequency" word=".)." count="6"/>
 <result title="frequency" word="Brain" count="6"/>
 <result title="frequency" word="Music" count="6"/>
 <result title="frequency" word="Neurosci" count="6"/>
 <result title="frequency" word="able" count="6"/>
 <result title="frequency" word="analysis" count="6"/>
 <result title="frequency" word="aspects" count="6"/>
 <result title="frequency" word="children" count="6"/>
 <result title="frequency" word="double;" count="6"/>
 <result title="frequency" word="high" count="6"/>
 <result title="frequency" word="musicians," count="6"/>
 <result title="frequency" word="normal" count="6"/>
 <result title="frequency" word="oddball" count="6"/>
 <result title="frequency" word="people" count="6"/>
 <result title="frequency" word="reaction" count="6"/>
 <result title="frequency" word="result" count="6"/>
 <result title="frequency" word="second" count="6"/>
 <result title="frequency" word="significant" count="6"/>
 <result title="frequency" word="total" count="6"/>
 <result title="frequency" word="(i.e.," count="5"/>
 <result title="frequency" word="ERP," count="5"/>
 <result title="frequency" word="Pantev" count="5"/>
 <result title="frequency" word="border-color" count="5"/>
 <result title="frequency" word="border-width" count="5"/>
 <result title="frequency" word="choice" count="5"/>
 <result title="frequency" word="compared" count="5"/>
 <result title="frequency" word="difference" count="5"/>
 <result title="frequency" word="discrimination" count="5"/>
 <result title="frequency" word="improved" count="5"/>
 <result title="frequency" word="means" count="5"/>
 <result title="frequency" word="measure" count="5"/>
 <result title="frequency" word="melodies" count="5"/>
 <result title="frequency" word="migraine" count="5"/>
 <result title="frequency" word="music," count="5"/>
 <result title="frequency" word="non-musician" count="5"/>
 <result title="frequency" word="non-target" count="5"/>
 <result title="frequency" word="plasticity" count="5"/>
 <result title="frequency" word="practice-induced" count="5"/>
 <result title="frequency" word="recording" count="5"/>
 <result title="frequency" word="scores" count="5"/>
 <result title="frequency" word="similar" count="5"/>
 <result title="frequency" word="small" count="5"/>
 <result title="frequency" word="solid;" count="5"/>
 <result title="frequency" word="testing" count="5"/>
 <result title="frequency" word="tone" count="5"/>
 <result title="frequency" word="working" count="5"/>
 <result title="frequency" word="years" count="5"/>
 <result title="frequency" word="{font-style" count="5"/>
 <result title="frequency" word="{font-weight" count="5"/>
 <result title="frequency" word="Correlation" count="4"/>
 <result title="frequency" word="EEG" count="4"/>
 <result title="frequency" word="Effects" count="4"/>
 <result title="frequency" word="Evers" count="4"/>
 <result title="frequency" word="Hantz" count="4"/>
 <result title="frequency" word="Musicians" count="4"/>
 <result title="frequency" word="Seashore-test" count="4"/>
 <result title="frequency" word="Significance" count="4"/>
 <result title="frequency" word="Trainor" count="4"/>
 <result title="frequency" word="bold" count="4"/>
 <result title="frequency" word="changes" count="4"/>
 <result title="frequency" word="components" count="4"/>
 <result title="frequency" word="cortical" count="4"/>
 <result title="frequency" word="courier;" count="4"/>
 <result title="frequency" word="duration" count="4"/>
 <result title="frequency" word="em;" count="4"/>
 <result title="frequency" word="enhanced" count="4"/>
 <result title="frequency" word="evidence" count="4"/>
 <result title="frequency" word="experiment" count="4"/>
 <result title="frequency" word="fast" count="4"/>
 <result title="frequency" word="important" count="4"/>
 <result title="frequency" word="interval" count="4"/>
 <result title="frequency" word="leads" count="4"/>
 <result title="frequency" word="lessons" count="4"/>
 <result title="frequency" word="level" count="4"/>
 <result title="frequency" word="loss" count="4"/>
 <result title="frequency" word="measures" count="4"/>
 <result title="frequency" word="melodic" count="4"/>
 <result title="frequency" word="mental" count="4"/>
 <result title="frequency" word="musician" count="4"/>
 <result title="frequency" word="musicians." count="4"/>
 <result title="frequency" word="musicians’" count="4"/>
 <result title="frequency" word="paradigm" count="4"/>
 <result title="frequency" word="phrase" count="4"/>
 <result title="frequency" word="previous" count="4"/>
 <result title="frequency" word="pt;}" count="4"/>
 <result title="frequency" word="relevant" count="4"/>
 <result title="frequency" word="separately" count="4"/>
 <result title="frequency" word="stimuli." count="4"/>
 <result title="frequency" word="structural" count="4"/>
 <result title="frequency" word="suggest" count="4"/>
 <result title="frequency" word="test," count="4"/>
</results>
